rio_metrics/collector.py
rio_metrics/middleware.py
django_riometrics_middleware-1.1.0.dist-info/LICENSE
django_riometrics_middleware-1.1.0.dist-info/METADATA
django_riometrics_middleware-1.1.0.dist-info/WHEEL
django_riometrics_middleware-1.1.0.dist-info/top_level.txt
django_riometrics_middleware-1.1.0.dist-info/RECORD
