Metadata-Version: 2.1
Name: django-riometrics-middleware
Version: 1.1.0
Summary: Rapyuta.io Metrics Django Middleware
Author: Rapyuta Robotics
Author-email: opensource@rapyuta-robotics.com
License: Apache 2.0
Requires-Python: >=3.6
License-File: LICENSE
Requires-Dist: requests (>=2.20.0)
Requires-Dist: urllib3 (>=1.23)
Requires-Dist: pytelegraf (==0.3.3)
Requires-Dist: setuptools
